jest/__init__.py
jest/magic.py
jest/tests/__init__.py
jest/tests/tests.py
pyjest-0.0.3.dist-info/LICENSE
pyjest-0.0.3.dist-info/METADATA
pyjest-0.0.3.dist-info/WHEEL
pyjest-0.0.3.dist-info/top_level.txt
pyjest-0.0.3.dist-info/RECORD
