Metadata-Version: 2.1
Name: pyjest
Version: 0.0.3
Summary: ipython magic tool to send HTTP requests in a cell of notebooks
Home-page: https://github.com/ozlerhakan/jest
Author: Hakan Ozler
Author-email: ozler.hakan@gmail.com
License: MIT
Project-URL: Bug Tracker, https://github.com/ozlerhakan/jest/issues
Keywords: python,magic tool,jupyter,notebook,jest
Platform: linux
Platform: unix
Classifier: Programming Language :: Python :: 3
Classifier: License :: OSI Approved :: MIT License
Classifier: Operating System :: OS Independent
Requires-Python: >=3.7
License-File: LICENSE
Requires-Dist: requests (==2.27.1)
Requires-Dist: ipython (==7.31.1)
Requires-Dist: tqdm (==4.62.3)
